latex_generators/__init__.py
latex_generators/generators.py
vsdmitri_latex_utils-1.0.2.dist-info/METADATA
vsdmitri_latex_utils-1.0.2.dist-info/WHEEL
vsdmitri_latex_utils-1.0.2.dist-info/top_level.txt
vsdmitri_latex_utils-1.0.2.dist-info/RECORD
