Metadata-Version: 2.4
Name: vsdmitri-latex-utils
Version: 1.0.2
Summary: LaTeX utils
